{"cache_path": "cache", "maximum_time": 62400, "distribution_mode": "mixed", "linear_temperature": {"duration": 100000000.0, "final_temperature": 1e-10, "initial_temperature": 0.01}, "uses_times": false, "proposal": "advanced", "quantiles": 20, "capacity_likelihood_alpha": 0.0001, "minimum_time": 0.0, "measurement_interval": 10000.0, "validation_interval": null, "relevant_modes": ["car", "pt", "bike", "walk"], "override_sigma": [], "total_iterations": 100000000.0, "constant_temperature": 1e-20, "_relevant_activity_types": [], "output_path": "output_1_notimes", "relevant_activity_types": ["shop", "leisure", "escort_kids", "escort_other", "remote_work"], "use_population_cache": false, "use_facilities_cache": false, "source_facilities_path": "data/lc_prepare/facilities_1.xml.gz", "exponential_temperature": {"duration": 100000000.0, "final_temperature": 1e-10, "initial_temperature": 0.01}, "capacity_scaling_factor": 0.01, "distance_based_proposal_candidate_set_size": 30, "schedule": "decay", "output_population_interval": 10000000.0, "time_bins": 288, "output_interval": 1000000.0, "source_population_path": "data/lc_prepare/population_1.xml.gz", "additional_activity_types": ["work", "education"]}